dash_model_viewer/DashModelViewer.py
dash_model_viewer/__init__.py
dash_model_viewer/_imports_.py
dash_model_viewer/dash_model_viewer.min.js
dash_model_viewer/dash_model_viewer.min.js.map
dash_model_viewer/metadata.json
dash_model_viewer/package-info.json
dash_model_viewer-0.0.1.dist-info/LICENSE
dash_model_viewer-0.0.1.dist-info/METADATA
dash_model_viewer-0.0.1.dist-info/WHEEL
dash_model_viewer-0.0.1.dist-info/top_level.txt
dash_model_viewer-0.0.1.dist-info/RECORD
