Metadata-Version: 2.2
Name: dash_model_viewer
Version: 0.0.1
Summary: Dynamic 3d AR modeling software for the Dash framework
Author: Pip Install Python LLC <pipinstallpython@gmail.com>
License: Apache-2.0
Classifier: Framework :: Dash
License-File: LICENSE
Dynamic: author
Dynamic: classifier
Dynamic: description
Dynamic: description-content-type
Dynamic: license
Dynamic: summary
